<annotation>
  <object>
    <name>short</name>
    <pose>Unspecified</pose>
    <truncated>0</truncated>
    <difficult>0</difficult>
    <bndbox>
      <xmin>1010</xmin>
      <xmax>1061</xmax>
      <ymin>1374</ymin>
      <ymax>1432</ymax>
    </bndbox>
  </object>
  <object>
    <name>short</name>
    <pose>Unspecified</pose>
    <truncated>0</truncated>
    <difficult>0</difficult>
    <bndbox>
      <xmin>1502</xmin>
      <xmax>1554</xmax>
      <ymin>1320</ymin>
      <ymax>1378</ymax>
    </bndbox>
  </object>
  <object>
    <name>short</name>
    <pose>Unspecified</pose>
    <truncated>0</truncated>
    <difficult>0</difficult>
    <bndbox>
      <xmin>2565</xmin>
      <xmax>2615</xmax>
      <ymin>548</ymin>
      <ymax>609</ymax>
    </bndbox>
  </object>
</annotation>
