<annotation>
  <object>
    <name>short</name>
    <pose>Unspecified</pose>
    <truncated>0</truncated>
    <difficult>0</difficult>
    <bndbox>
      <xmin>617</xmin>
      <xmax>671</xmax>
      <ymin>1936</ymin>
      <ymax>2018</ymax>
    </bndbox>
  </object>
  <object>
    <name>short</name>
    <pose>Unspecified</pose>
    <truncated>0</truncated>
    <difficult>0</difficult>
    <bndbox>
      <xmin>347</xmin>
      <xmax>401</xmax>
      <ymin>1681</ymin>
      <ymax>1733</ymax>
    </bndbox>
  </object>
  <object>
    <name>short</name>
    <pose>Unspecified</pose>
    <truncated>0</truncated>
    <difficult>0</difficult>
    <bndbox>
      <xmin>725</xmin>
      <xmax>781</xmax>
      <ymin>1213</ymin>
      <ymax>1277</ymax>
    </bndbox>
  </object>
  <object>
    <name>short</name>
    <pose>Unspecified</pose>
    <truncated>0</truncated>
    <difficult>0</difficult>
    <bndbox>
      <xmin>2263</xmin>
      <xmax>2323</xmax>
      <ymin>1210</ymin>
      <ymax>1265</ymax>
    </bndbox>
  </object>
  <object>
    <name>short</name>
    <pose>Unspecified</pose>
    <truncated>0</truncated>
    <difficult>0</difficult>
    <bndbox>
      <xmin>2030</xmin>
      <xmax>2121</xmax>
      <ymin>743</ymin>
      <ymax>804</ymax>
    </bndbox>
  </object>
</annotation>
