<annotation>
  <object>
    <name>spur</name>
    <pose>Unspecified</pose>
    <truncated>0</truncated>
    <difficult>0</difficult>
    <bndbox>
      <xmin>1739</xmin>
      <xmax>1818</xmax>
      <ymin>1343</ymin>
      <ymax>1401</ymax>
    </bndbox>
  </object>
  <object>
    <name>spur</name>
    <pose>Unspecified</pose>
    <truncated>0</truncated>
    <difficult>0</difficult>
    <bndbox>
      <xmin>374</xmin>
      <xmax>471</xmax>
      <ymin>1289</ymin>
      <ymax>1339</ymax>
    </bndbox>
  </object>
  <object>
    <name>spur</name>
    <pose>Unspecified</pose>
    <truncated>0</truncated>
    <difficult>0</difficult>
    <bndbox>
      <xmin>1525</xmin>
      <xmax>1615</xmax>
      <ymin>1089</ymin>
      <ymax>1182</ymax>
    </bndbox>
  </object>
  <object>
    <name>spur</name>
    <pose>Unspecified</pose>
    <truncated>0</truncated>
    <difficult>0</difficult>
    <bndbox>
      <xmin>708</xmin>
      <xmax>797</xmax>
      <ymin>814</ymin>
      <ymax>875</ymax>
    </bndbox>
  </object>
  <object>
    <name>spur</name>
    <pose>Unspecified</pose>
    <truncated>0</truncated>
    <difficult>0</difficult>
    <bndbox>
      <xmin>1410</xmin>
      <xmax>1504</xmax>
      <ymin>325</ymin>
      <ymax>379</ymax>
    </bndbox>
  </object>
</annotation>
