<annotation>
  <object>
    <name>spur</name>
    <pose>Unspecified</pose>
    <truncated>0</truncated>
    <difficult>0</difficult>
    <bndbox>
      <xmin>984</xmin>
      <xmax>1046</xmax>
      <ymin>1422</ymin>
      <ymax>1520</ymax>
    </bndbox>
  </object>
  <object>
    <name>spur</name>
    <pose>Unspecified</pose>
    <truncated>0</truncated>
    <difficult>0</difficult>
    <bndbox>
      <xmin>1537</xmin>
      <xmax>1592</xmax>
      <ymin>1284</ymin>
      <ymax>1389</ymax>
    </bndbox>
  </object>
  <object>
    <name>spur</name>
    <pose>Unspecified</pose>
    <truncated>0</truncated>
    <difficult>0</difficult>
    <bndbox>
      <xmin>1066</xmin>
      <xmax>1137</xmax>
      <ymin>1032</ymin>
      <ymax>1157</ymax>
    </bndbox>
  </object>
  <object>
    <name>spur</name>
    <pose>Unspecified</pose>
    <truncated>0</truncated>
    <difficult>0</difficult>
    <bndbox>
      <xmin>1124</xmin>
      <xmax>1225</xmax>
      <ymin>714</ymin>
      <ymax>815</ymax>
    </bndbox>
  </object>
  <object>
    <name>spur</name>
    <pose>Unspecified</pose>
    <truncated>0</truncated>
    <difficult>0</difficult>
    <bndbox>
      <xmin>1699</xmin>
      <xmax>1795</xmax>
      <ymin>550</ymin>
      <ymax>644</ymax>
    </bndbox>
  </object>
</annotation>
